phytorch/__init__.py
phytorch/fit.py
phytorch/core/__init__.py
phytorch/core/result.py
phytorch/core/optimizers/__init__.py
phytorch/core/optimizers/scipy_optimizer.py
phytorch/core/optimizers/torch_optimizer.py
phytorch/data/__init__.py
phytorch/data/fvcb/curves/iceberg/curves.csv
phytorch/data/stomatal/curves/steadystate_stomatalconductance.csv
phytorch/data/stomatal/survey/nonsteadystate_stomatalconductance.csv
phytorch/data/stomatal/survey/iceberg/Iceberg_poro.csv
phytorch/data/tests/__init__.py
phytorch/data/tests/dfMAGIC043_lr.csv
phytorch/data/tests/nonsteadystate_stomatalconductance.csv
phytorch/data/tests/steadystate_stomatalconductance.csv
phytorch/models/__init__.py
phytorch/models/base.py
phytorch/models/canopy/__init__.py
phytorch/models/canopy/leaf_angle_distribution.py
phytorch/models/canopy/utils.py
phytorch/models/generic/__init__.py
phytorch/models/generic/arrhenius.py
phytorch/models/generic/beta.py
phytorch/models/generic/gaussian.py
phytorch/models/generic/linear.py
phytorch/models/generic/nonrectangular_hyperbola.py
phytorch/models/generic/peaked_arrhenius.py
phytorch/models/generic/rectangular_hyperbola.py
phytorch/models/generic/sigmoidal.py
phytorch/models/generic/weibull.py
phytorch/models/hydraulics/__init__.py
phytorch/models/hydraulics/sigmoidal.py
phytorch/models/hydraulics/sjb2018.py
phytorch/models/leafoptics/__init__.py
phytorch/models/leafoptics/inverseprospect.py
phytorch/models/leafoptics/prospectmodels.py
phytorch/models/photosynthesis/__init__.py
phytorch/models/photosynthesis/fvcb.py
phytorch/models/photosynthesis/fvcb_core_legacy.py
phytorch/models/photosynthesis/fvcb_data_legacy.py
phytorch/models/stomatal/__init__.py
phytorch/models/stomatal/bbl1995.py
phytorch/models/stomatal/bta2012.py
phytorch/models/stomatal/bwb1987.py
phytorch/models/stomatal/med2011.py
phytorch/utilities/__init__.py
phytorch/utilities/correct_LI600.py
phytorch/utilities/porometer.py
phytorch/utilities/spectral.py
phytorch_lib-0.1.5.dist-info/licenses/LICENSE
phytorch_lib-0.1.5.dist-info/METADATA
phytorch_lib-0.1.5.dist-info/WHEEL
phytorch_lib-0.1.5.dist-info/top_level.txt
phytorch_lib-0.1.5.dist-info/RECORD
