Metadata-Version: 2.4
Name: phytorch-lib
Version: 0.1.5
Summary: PhyTorch is a PyTorch-based modeling toolkit for fitting common plant physiological models of photosynthesis, stomatal conductance, leaf hydraulics, and optical properties.
Home-page: https://github.com/ktrizzo/phytorch
Author: Tong Lei, Kyle T. Rizzo, Brian N. Bailey
Author-email: 
Keywords: photosynthesis stomatal-conductance hydraulics optics plant-physiology pytorch
Classifier: Development Status :: 3 - Alpha
Classifier: Programming Language :: Python :: 3
Classifier: Programming Language :: Python :: 3.7
Classifier: Programming Language :: Python :: 3.8
Classifier: Programming Language :: Python :: 3.9
Classifier: Programming Language :: Python :: 3.10
Classifier: Programming Language :: Python :: 3.11
Classifier: Intended Audience :: Science/Research
Classifier: Topic :: Scientific/Engineering :: Bio-Informatics
Classifier: Topic :: Scientific/Engineering :: Physics
Classifier: License :: OSI Approved :: GNU General Public License v3 (GPLv3)
Requires-Python: >=3.7
License-File: LICENSE
Requires-Dist: torch>=1.9.0
Requires-Dist: numpy>=1.19.0
Requires-Dist: pandas>=1.1.0
Requires-Dist: scipy>=1.5.0
Requires-Dist: matplotlib>=3.3.0
Dynamic: author
Dynamic: classifier
Dynamic: description
Dynamic: description-content-type
Dynamic: home-page
Dynamic: keywords
Dynamic: license-file
Dynamic: requires-dist
Dynamic: requires-python
Dynamic: summary
